<?xml version="1.0" encoding="utf-8"?>
<metasee>
	<datasets>
		<dataset>CAM_SMPL_SRA022130</dataset>
	</datasets>
	<node name="root">
	<count><val>182</val></count>
		<node name="Bacteria">
		<count><val>168</val></count>
			<node name="Proteobacteria">
			<count><val>86</val></count>
				<node name="Alphaproteobacteria">
				<count><val>43</val></count>
					<node name="Rhodobacterales">
					<count><val>41</val></count>
						<node name="Rhodobacteraceae">
						<count><val>41</val></count>
							<node name="Roseovarius">
							<count><val>31</val></count>
								<node name="Unclassified">
								<count><val>31</val></count>
								</node>
							</node>
							<node name="Roseobacter">
							<count><val>2</val></count>
								<node name="Unclassified">
								<count><val>2</val></count>
								</node>
							</node>
							<node name="Unclassified">
							<count><val>3</val></count>
							</node>
							<node name="Rhodobacter">
							<count><val>2</val></count>
								<node name="Unclassified">
								<count><val>2</val></count>
								</node>
							</node>
							<node name="Paracoccus">
							<count><val>3</val></count>
								<node name="Unclassified">
								<count><val>3</val></count>
								</node>
							</node>
						</node>
					</node>
					<node name="Caulobacterales">
					<count><val>1</val></count>
						<node name="Caulobacteraceae">
						<count><val>1</val></count>
							<node name="Caulobacter">
							<count><val>1</val></count>
								<node name="Unclassified">
								<count><val>1</val></count>
								</node>
							</node>
						</node>
					</node>
					<node name="Unclassified">
					<count><val>1</val></count>
					</node>
				</node>
				<node name="Gammaproteobacteria">
				<count><val>40</val></count>
					<node name="Oceanospirillales">
					<count><val>8</val></count>
						<node name="Oceanospirillum">
						<count><val>7</val></count>
							<node name="Unclassified">
							<count><val>7</val></count>
							</node>
						</node>
						<node name="Halomonadaceae">
						<count><val>1</val></count>
							<node name="Halomonas">
							<count><val>1</val></count>
								<node name="Unclassified">
								<count><val>1</val></count>
								</node>
							</node>
						</node>
					</node>
					<node name="Alteromonadales">
					<count><val>29</val></count>
						<node name="Alteromonadaceae">
						<count><val>24</val></count>
							<node name="Marinobacter">
							<count><val>24</val></count>
								<node name="Unclassified">
								<count><val>24</val></count>
								</node>
							</node>
						</node>
						<node name="Psychromonadaceae">
						<count><val>4</val></count>
							<node name="Psychromonas">
							<count><val>4</val></count>
								<node name="Unclassified">
								<count><val>4</val></count>
								</node>
							</node>
						</node>
						<node name="Colwelliaceae">
						<count><val>1</val></count>
							<node name="Colwellia">
							<count><val>1</val></count>
								<node name="Unclassified">
								<count><val>1</val></count>
								</node>
							</node>
						</node>
					</node>
					<node name="Unclassified">
					<count><val>1</val></count>
					</node>
					<node name="Thiotrichales">
					<count><val>1</val></count>
						<node name="Piscirickettsiaceae">
						<count><val>1</val></count>
							<node name="Thiomicrospira">
							<count><val>1</val></count>
								<node name="Unclassified">
								<count><val>1</val></count>
								</node>
							</node>
						</node>
					</node>
					<node name="Methylococcales">
					<count><val>1</val></count>
						<node name="Methylococcaceae">
						<count><val>1</val></count>
							<node name="Methylobacter">
							<count><val>1</val></count>
								<node name="Unclassified">
								<count><val>1</val></count>
								</node>
							</node>
						</node>
					</node>
				</node>
				<node name="Deltaproteobacteria">
				<count><val>2</val></count>
					<node name="Desulfobacterales">
					<count><val>2</val></count>
						<node name="Desulfobacteraceae">
						<count><val>2</val></count>
							<node name="Desulfobacter">
							<count><val>2</val></count>
								<node name="Unclassified">
								<count><val>2</val></count>
								</node>
							</node>
						</node>
					</node>
				</node>
				<node name="Epsilonproteobacteria">
				<count><val>1</val></count>
					<node name="Unclassified">
					<count><val>1</val></count>
					</node>
				</node>
			</node>
			<node name="Unclassified">
			<count><val>16</val></count>
			</node>
			<node name="Bacteroidetes">
			<count><val>48</val></count>
				<node name="Flavobacteria">
				<count><val>43</val></count>
					<node name="Flavobacteriales">
					<count><val>43</val></count>
						<node name="Flavobacteriaceae">
						<count><val>43</val></count>
							<node name="Psychroflexus">
							<count><val>34</val></count>
								<node name="Unclassified">
								<count><val>34</val></count>
								</node>
							</node>
							<node name="Unclassified">
							<count><val>6</val></count>
							</node>
							<node name="Pibocella">
							<count><val>1</val></count>
							</node>
							<node name="Gelidibacter">
							<count><val>1</val></count>
								<node name="Unclassified">
								<count><val>1</val></count>
								</node>
							</node>
							<node name="Polaribacter">
							<count><val>1</val></count>
								<node name="Unclassified">
								<count><val>1</val></count>
								</node>
							</node>
						</node>
					</node>
				</node>
				<node name="Sphingobacteria">
				<count><val>2</val></count>
					<node name="Sphingobacteriales">
					<count><val>2</val></count>
						<node name="Flexibacteraceae">
						<count><val>2</val></count>
							<node name="Algoriphagus">
							<count><val>1</val></count>
								<node name="Unclassified">
								<count><val>1</val></count>
								</node>
							</node>
							<node name="Flexibacter">
							<count><val>1</val></count>
								<node name="Unclassified">
								<count><val>1</val></count>
								</node>
							</node>
						</node>
					</node>
				</node>
				<node name="Bacteroidales">
				<count><val>1</val></count>
					<node name="Rikenellaceae">
					<count><val>1</val></count>
						<node name="Ruminofilibacter">
						<count><val>1</val></count>
						</node>
					</node>
				</node>
				<node name="Unclassified">
				<count><val>2</val></count>
				</node>
			</node>
			<node name="Actinobacteria">
			<count><val>6</val></count>
				<node name="Actinobacteridae">
				<count><val>6</val></count>
					<node name="Actinomycetales">
					<count><val>6</val></count>
						<node name="Micrococcineae">
						<count><val>6</val></count>
							<node name="Microbacteriaceae">
							<count><val>6</val></count>
								<node name="Cryocola">
								<count><val>3</val></count>
								</node>
								<node name="Unclassified">
								<count><val>2</val></count>
								</node>
								<node name="Microbacterium">
								<count><val>1</val></count>
									<node name="Unclassified">
									<count><val>1</val></count>
									</node>
								</node>
							</node>
						</node>
					</node>
				</node>
			</node>
			<node name="Firmicutes">
			<count><val>7</val></count>
				<node name="Bacillales">
				<count><val>7</val></count>
					<node name="Macrococcus">
					<count><val>7</val></count>
					</node>
				</node>
			</node>
			<node name="Verrucomicrobia">
			<count><val>1</val></count>
				<node name="Verrucomicrobia">
				<count><val>1</val></count>
					<node name="Unclassified">
					<count><val>1</val></count>
					</node>
				</node>
			</node>
			<node name="Spirochaetes">
			<count><val>1</val></count>
				<node name="Spirochaetales">
				<count><val>1</val></count>
					<node name="Spirochaetaceae">
					<count><val>1</val></count>
						<node name="Spirochaeta">
						<count><val>1</val></count>
							<node name="Unclassified">
							<count><val>1</val></count>
							</node>
						</node>
					</node>
				</node>
			</node>
			<node name="Nitrospirae">
			<count><val>3</val></count>
				<node name="Nitrospirales">
				<count><val>3</val></count>
					<node name="Nitrospiraceae">
					<count><val>3</val></count>
						<node name="Nitrospira">
						<count><val>3</val></count>
							<node name="Unclassified">
							<count><val>3</val></count>
							</node>
						</node>
					</node>
				</node>
			</node>
		</node>
		<node name="Eukaryota">
		<count><val>14</val></count>
			<node name="stramenopiles">
			<count><val>4</val></count>
				<node name="Bacillariophyta">
				<count><val>4</val></count>
					<node name="Coscinodiscophyceae">
					<count><val>4</val></count>
						<node name="Thalassiosirophycidae">
						<count><val>4</val></count>
							<node name="Thalassiosirales">
							<count><val>4</val></count>
								<node name="Thalassiosiraceae">
								<count><val>4</val></count>
									<node name="Thalassiosira">
									<count><val>4</val></count>
									</node>
								</node>
							</node>
						</node>
					</node>
				</node>
			</node>
			<node name="Viridiplantae">
			<count><val>9</val></count>
				<node name="Streptophyta">
				<count><val>9</val></count>
					<node name="Embryophyta">
					<count><val>9</val></count>
						<node name="Bryophyta">
						<count><val>9</val></count>
							<node name="Bryopsida">
							<count><val>9</val></count>
								<node name="Funariidae">
								<count><val>9</val></count>
									<node name="Funariales">
									<count><val>9</val></count>
										<node name="Funariaceae">
										<count><val>9</val></count>
											<node name="Physcomitrella">
											<count><val>9</val></count>
											</node>
										</node>
									</node>
								</node>
							</node>
						</node>
					</node>
				</node>
			</node>
			<node name="Cryptophyta">
			<count><val>1</val></count>
				<node name="Cryptomonadaceae">
				<count><val>1</val></count>
					<node name="Pyrenomonas">
					<count><val>1</val></count>
					</node>
				</node>
			</node>
		</node>
	</node>
</metasee>
