<?xml version="1.0" encoding="utf-8"?>
<metasee>
	<datasets>
		<dataset>CAM_SMPL_SRA022176</dataset>
	</datasets>
	<node name="root">
	<count><val>441</val></count>
		<node name="Bacteria">
		<count><val>336</val></count>
			<node name="Proteobacteria">
			<count><val>234</val></count>
				<node name="Gammaproteobacteria">
				<count><val>64</val></count>
					<node name="Nitrincola">
					<count><val>8</val></count>
					</node>
					<node name="symbionts">
					<count><val>32</val></count>
						<node name="Unclassified">
						<count><val>32</val></count>
						</node>
					</node>
					<node name="Unclassified">
					<count><val>2</val></count>
					</node>
					<node name="Oceanospirillales">
					<count><val>3</val></count>
						<node name="Neptunomonas">
						<count><val>1</val></count>
							<node name="Unclassified">
							<count><val>1</val></count>
							</node>
						</node>
						<node name="Oceanospirillum">
						<count><val>2</val></count>
							<node name="Unclassified">
							<count><val>2</val></count>
							</node>
						</node>
					</node>
					<node name="Alteromonadales">
					<count><val>7</val></count>
						<node name="Colwelliaceae">
						<count><val>1</val></count>
							<node name="Colwellia">
							<count><val>1</val></count>
								<node name="Unclassified">
								<count><val>1</val></count>
								</node>
							</node>
						</node>
						<node name="Alteromonadaceae">
						<count><val>3</val></count>
							<node name="Marinobacterium">
							<count><val>3</val></count>
								<node name="Unclassified">
								<count><val>3</val></count>
								</node>
							</node>
						</node>
						<node name="Pseudoalteromonadaceae">
						<count><val>3</val></count>
							<node name="Pseudoalteromonas">
							<count><val>3</val></count>
								<node name="Unclassified">
								<count><val>3</val></count>
								</node>
							</node>
						</node>
					</node>
					<node name="Pseudomonadales">
					<count><val>2</val></count>
						<node name="Pseudomonadaceae">
						<count><val>1</val></count>
							<node name="Pseudomonas">
							<count><val>1</val></count>
								<node name="Unclassified">
								<count><val>1</val></count>
								</node>
							</node>
						</node>
						<node name="Moraxellaceae">
						<count><val>1</val></count>
							<node name="Moraxella">
							<count><val>1</val></count>
								<node name="Unclassified">
								<count><val>1</val></count>
								</node>
							</node>
						</node>
					</node>
					<node name="Chromatiales">
					<count><val>7</val></count>
						<node name="Ectothiorhodospiraceae">
						<count><val>7</val></count>
							<node name="Thiohalospira">
							<count><val>3</val></count>
							</node>
							<node name="Thioalkalivibrio">
							<count><val>3</val></count>
								<node name="Unclassified">
								<count><val>3</val></count>
								</node>
							</node>
							<node name="Alkalilimnicola">
							<count><val>1</val></count>
							</node>
						</node>
					</node>
					<node name="Thiohalomonas">
					<count><val>1</val></count>
					</node>
					<node name="Thiotrichales">
					<count><val>1</val></count>
						<node name="Francisellaceae">
						<count><val>1</val></count>
							<node name="Francisella">
							<count><val>1</val></count>
								<node name="Unclassified">
								<count><val>1</val></count>
								</node>
							</node>
						</node>
					</node>
					<node name="Legionellales">
					<count><val>1</val></count>
						<node name="Legionellaceae">
						<count><val>1</val></count>
							<node name="Legionella">
							<count><val>1</val></count>
								<node name="Unclassified">
								<count><val>1</val></count>
								</node>
							</node>
						</node>
					</node>
				</node>
				<node name="Alphaproteobacteria">
				<count><val>123</val></count>
					<node name="Sphingomonadales">
					<count><val>42</val></count>
						<node name="Erythrobacteraceae">
						<count><val>6</val></count>
							<node name="Erythrobacter">
							<count><val>6</val></count>
								<node name="Unclassified">
								<count><val>6</val></count>
								</node>
							</node>
						</node>
						<node name="Sphingomonadaceae">
						<count><val>36</val></count>
							<node name="Unclassified">
							<count><val>28</val></count>
							</node>
							<node name="Sphingomonas">
							<count><val>8</val></count>
								<node name="Unclassified">
								<count><val>8</val></count>
								</node>
							</node>
						</node>
					</node>
					<node name="Rhizobiales">
					<count><val>76</val></count>
						<node name="Brucellaceae">
						<count><val>41</val></count>
							<node name="Unclassified">
							<count><val>41</val></count>
							</node>
						</node>
						<node name="Rhizobiaceae">
						<count><val>26</val></count>
							<node name="group">
							<count><val>26</val></count>
								<node name="Rhizobium">
								<count><val>26</val></count>
									<node name="Unclassified">
									<count><val>26</val></count>
									</node>
								</node>
							</node>
						</node>
						<node name="Methylobacteriaceae">
						<count><val>3</val></count>
							<node name="Roseomonas">
							<count><val>3</val></count>
							</node>
						</node>
						<node name="Phyllobacteriaceae">
						<count><val>4</val></count>
							<node name="Mesorhizobium">
							<count><val>4</val></count>
								<node name="Unclassified">
								<count><val>4</val></count>
								</node>
							</node>
						</node>
						<node name="Beijerinckiaceae">
						<count><val>1</val></count>
							<node name="Chelatococcus">
							<count><val>1</val></count>
								<node name="Unclassified">
								<count><val>1</val></count>
								</node>
							</node>
						</node>
						<node name="Hyphomicrobiaceae">
						<count><val>1</val></count>
							<node name="Devosia">
							<count><val>1</val></count>
								<node name="Unclassified">
								<count><val>1</val></count>
								</node>
							</node>
						</node>
					</node>
					<node name="Rhodospirillales">
					<count><val>3</val></count>
						<node name="Acetobacteraceae">
						<count><val>1</val></count>
							<node name="Stella">
							<count><val>1</val></count>
								<node name="Unclassified">
								<count><val>1</val></count>
								</node>
							</node>
						</node>
						<node name="Rhodospirillaceae">
						<count><val>2</val></count>
							<node name="Magnetospirillum">
							<count><val>2</val></count>
								<node name="Unclassified">
								<count><val>2</val></count>
								</node>
							</node>
						</node>
					</node>
					<node name="Unclassified">
					<count><val>2</val></count>
					</node>
				</node>
				<node name="Deltaproteobacteria">
				<count><val>44</val></count>
					<node name="Desulfovibrionales">
					<count><val>2</val></count>
						<node name="Desulfovibrionaceae">
						<count><val>2</val></count>
							<node name="Desulfovibrio">
							<count><val>2</val></count>
								<node name="Unclassified">
								<count><val>2</val></count>
								</node>
							</node>
						</node>
					</node>
					<node name="Desulfuromonadales">
					<count><val>24</val></count>
						<node name="Desulfuromonadaceae">
						<count><val>2</val></count>
							<node name="Desulfuromonas">
							<count><val>2</val></count>
								<node name="Unclassified">
								<count><val>2</val></count>
								</node>
							</node>
						</node>
						<node name="Geobacteraceae">
						<count><val>21</val></count>
							<node name="Geobacter">
							<count><val>21</val></count>
								<node name="Unclassified">
								<count><val>21</val></count>
								</node>
							</node>
						</node>
						<node name="Pelobacteraceae">
						<count><val>1</val></count>
							<node name="Pelobacter">
							<count><val>1</val></count>
								<node name="Unclassified">
								<count><val>1</val></count>
								</node>
							</node>
						</node>
					</node>
					<node name="Unclassified">
					<count><val>16</val></count>
					</node>
					<node name="Myxococcales">
					<count><val>1</val></count>
						<node name="Cystobacterineae">
						<count><val>1</val></count>
							<node name="Myxococcaceae">
							<count><val>1</val></count>
								<node name="Myxococcus">
								<count><val>1</val></count>
								</node>
							</node>
						</node>
					</node>
					<node name="Syntrophobacterales">
					<count><val>1</val></count>
						<node name="Syntrophobacteraceae">
						<count><val>1</val></count>
							<node name="Thermodesulforhabdus">
							<count><val>1</val></count>
							</node>
						</node>
					</node>
				</node>
				<node name="Unclassified">
				<count><val>2</val></count>
				</node>
				<node name="Epsilonproteobacteria">
				<count><val>1</val></count>
					<node name="Nautiliales">
					<count><val>1</val></count>
						<node name="Nautiliaceae">
						<count><val>1</val></count>
							<node name="Caminibacter">
							<count><val>1</val></count>
							</node>
						</node>
					</node>
				</node>
			</node>
			<node name="Nitrospirae">
			<count><val>11</val></count>
				<node name="Nitrospirales">
				<count><val>11</val></count>
					<node name="Nitrospiraceae">
					<count><val>11</val></count>
						<node name="Thermodesulfovibrio">
						<count><val>9</val></count>
							<node name="Unclassified">
							<count><val>9</val></count>
							</node>
						</node>
						<node name="Nitrospira">
						<count><val>2</val></count>
							<node name="Unclassified">
							<count><val>2</val></count>
							</node>
						</node>
					</node>
				</node>
			</node>
			<node name="Actinobacteria">
			<count><val>43</val></count>
				<node name="Actinobacteridae">
				<count><val>34</val></count>
					<node name="Actinomycetales">
					<count><val>34</val></count>
						<node name="Pseudonocardineae">
						<count><val>31</val></count>
							<node name="Pseudonocardiaceae">
							<count><val>31</val></count>
								<node name="Saccharopolyspora">
								<count><val>31</val></count>
								</node>
							</node>
						</node>
						<node name="Micrococcineae">
						<count><val>1</val></count>
							<node name="Intrasporangiaceae">
							<count><val>1</val></count>
								<node name="II">
								<count><val>1</val></count>
								</node>
							</node>
						</node>
						<node name="Frankineae">
						<count><val>1</val></count>
							<node name="Frankiaceae">
							<count><val>1</val></count>
								<node name="Unclassified">
								<count><val>1</val></count>
								</node>
							</node>
						</node>
						<node name="Streptomycineae">
						<count><val>1</val></count>
							<node name="Streptomycetaceae">
							<count><val>1</val></count>
								<node name="Streptomyces">
								<count><val>1</val></count>
									<node name="Unclassified">
									<count><val>1</val></count>
									</node>
								</node>
							</node>
						</node>
					</node>
				</node>
				<node name="Microthrix">
				<count><val>8</val></count>
					<node name="Unclassified">
					<count><val>8</val></count>
					</node>
				</node>
				<node name="Acidimicrobidae">
				<count><val>1</val></count>
					<node name="Unclassified">
					<count><val>1</val></count>
					</node>
				</node>
			</node>
			<node name="Fusobacteria">
			<count><val>1</val></count>
				<node name="Fusobacterales">
				<count><val>1</val></count>
					<node name="sedis">
					<count><val>1</val></count>
						<node name="Cetobacterium">
						<count><val>1</val></count>
						</node>
					</node>
				</node>
			</node>
			<node name="Unclassified">
			<count><val>6</val></count>
			</node>
			<node name="Bacteroidetes">
			<count><val>13</val></count>
				<node name="Unclassified">
				<count><val>4</val></count>
				</node>
				<node name="Flavobacteria">
				<count><val>8</val></count>
					<node name="Flavobacteriales">
					<count><val>8</val></count>
						<node name="Flavobacteriaceae">
						<count><val>8</val></count>
							<node name="Cellulophaga">
							<count><val>4</val></count>
								<node name="Unclassified">
								<count><val>4</val></count>
								</node>
							</node>
							<node name="Psychroserpens">
							<count><val>4</val></count>
							</node>
						</node>
					</node>
				</node>
				<node name="Sphingobacteria">
				<count><val>1</val></count>
					<node name="Sphingobacteriales">
					<count><val>1</val></count>
						<node name="Flexibacteraceae">
						<count><val>1</val></count>
							<node name="Cytophaga">
							<count><val>1</val></count>
								<node name="Unclassified">
								<count><val>1</val></count>
								</node>
							</node>
						</node>
					</node>
				</node>
			</node>
			<node name="Verrucomicrobia">
			<count><val>7</val></count>
				<node name="Verrucomicrobia">
				<count><val>7</val></count>
					<node name="Unclassified">
					<count><val>7</val></count>
					</node>
				</node>
			</node>
			<node name="Thermobaculum">
			<count><val>3</val></count>
			</node>
			<node name="Acidobacteria">
			<count><val>2</val></count>
				<node name="Acidobacteriales">
				<count><val>2</val></count>
					<node name="Acidobacteriaceae">
					<count><val>2</val></count>
						<node name="Holophaga">
						<count><val>1</val></count>
							<node name="Unclassified">
							<count><val>1</val></count>
							</node>
						</node>
						<node name="Unclassified">
						<count><val>1</val></count>
						</node>
					</node>
				</node>
			</node>
			<node name="Firmicutes">
			<count><val>9</val></count>
				<node name="Clostridia">
				<count><val>9</val></count>
					<node name="Clostridiales">
					<count><val>8</val></count>
						<node name="Syntrophomonadaceae">
						<count><val>3</val></count>
							<node name="Thermaerobacter">
							<count><val>3</val></count>
							</node>
						</node>
						<node name="Clostridiaceae">
						<count><val>2</val></count>
							<node name="Clostridium">
							<count><val>2</val></count>
								<node name="Unclassified">
								<count><val>2</val></count>
								</node>
							</node>
						</node>
						<node name="Sedis">
						<count><val>3</val></count>
							<node name="Thermaerobacter">
							<count><val>3</val></count>
							</node>
						</node>
					</node>
					<node name="Thermoanaerobacteriales">
					<count><val>1</val></count>
						<node name="Thermoanaerobacteriaceae">
						<count><val>1</val></count>
							<node name="Thermoanaerobacter">
							<count><val>1</val></count>
								<node name="Unclassified">
								<count><val>1</val></count>
								</node>
							</node>
						</node>
					</node>
				</node>
			</node>
			<node name="Chloroflexi">
			<count><val>2</val></count>
				<node name="Anaerolineae">
				<count><val>1</val></count>
					<node name="Anaerolinaeles">
					<count><val>1</val></count>
						<node name="Anaerolinaceae">
						<count><val>1</val></count>
							<node name="Caldilinea">
							<count><val>1</val></count>
							</node>
						</node>
					</node>
				</node>
				<node name="Dehalococcoidetes">
				<count><val>1</val></count>
					<node name="Dehalococcoides">
					<count><val>1</val></count>
						<node name="Unclassified">
						<count><val>1</val></count>
						</node>
					</node>
				</node>
			</node>
			<node name="Planctomycetes">
			<count><val>5</val></count>
				<node name="Planctomycetacia">
				<count><val>5</val></count>
					<node name="Planctomycetales">
					<count><val>5</val></count>
						<node name="Planctomycetaceae">
						<count><val>5</val></count>
							<node name="Pirellula">
							<count><val>1</val></count>
								<node name="Unclassified">
								<count><val>1</val></count>
								</node>
							</node>
							<node name="Unclassified">
							<count><val>1</val></count>
							</node>
							<node name="Planctomyces">
							<count><val>3</val></count>
								<node name="Unclassified">
								<count><val>3</val></count>
								</node>
							</node>
						</node>
					</node>
				</node>
			</node>
		</node>
		<node name="Eukaryota">
		<count><val>8</val></count>
			<node name="Metazoa">
			<count><val>6</val></count>
				<node name="Mollusca">
				<count><val>6</val></count>
					<node name="Bivalvia">
					<count><val>6</val></count>
						<node name="Heteroconchia">
						<count><val>6</val></count>
							<node name="Veneroida">
							<count><val>6</val></count>
								<node name="Glossoidea">
								<count><val>6</val></count>
									<node name="Vesicomyidae">
									<count><val>6</val></count>
										<node name="Calyptogena">
										<count><val>6</val></count>
										</node>
									</node>
								</node>
							</node>
						</node>
					</node>
				</node>
			</node>
			<node name="Rhodophyta">
			<count><val>2</val></count>
				<node name="Bangiophyceae">
				<count><val>2</val></count>
					<node name="Bangiales">
					<count><val>2</val></count>
						<node name="Bangiaceae">
						<count><val>2</val></count>
							<node name="Porphyra">
							<count><val>2</val></count>
							</node>
						</node>
					</node>
				</node>
			</node>
		</node>
		<node name="Archaea">
		<count><val>97</val></count>
			<node name="Euryarchaeota">
			<count><val>97</val></count>
				<node name="Methanopyri">
				<count><val>63</val></count>
					<node name="Methanopyrales">
					<count><val>63</val></count>
						<node name="Methanopyraceae">
						<count><val>63</val></count>
							<node name="Methanopyrus">
							<count><val>63</val></count>
								<node name="Unclassified">
								<count><val>63</val></count>
								</node>
							</node>
						</node>
					</node>
				</node>
				<node name="Archaeoglobi">
				<count><val>1</val></count>
					<node name="Archaeoglobales">
					<count><val>1</val></count>
						<node name="Archaeoglobaceae">
						<count><val>1</val></count>
							<node name="Archaeoglobus">
							<count><val>1</val></count>
							</node>
						</node>
					</node>
				</node>
				<node name="Methanococci">
				<count><val>5</val></count>
					<node name="Methanococcales">
					<count><val>5</val></count>
						<node name="Methanococcaceae">
						<count><val>5</val></count>
							<node name="Methanococcus">
							<count><val>5</val></count>
								<node name="Unclassified">
								<count><val>5</val></count>
								</node>
							</node>
						</node>
					</node>
				</node>
				<node name="Halobacteria">
				<count><val>28</val></count>
					<node name="Halobacteriales">
					<count><val>28</val></count>
						<node name="Halobacteriaceae">
						<count><val>28</val></count>
							<node name="Natronomonas">
							<count><val>26</val></count>
							</node>
							<node name="Halogeometricum">
							<count><val>2</val></count>
							</node>
						</node>
					</node>
				</node>
			</node>
		</node>
	</node>
</metasee>
